{"type":"TOPS","count":55,"updated":"2026-05-14T12:29:07","products":[{"seller":"hotdog-official","brand":"Broken Planet","type":"TOPS","title":"（¥129+¥155）Football Set","yupoo":"https://hotdog-official.x.yupoo.com/albums/179202385?uid=1&isSubCate=false&referrercate=4098105","kakobuy":"https://www.kakobuy.com/item/details?url=https%3A%2F%2Fshop1621342910.v.weidian.com%2Fitem.html%3FitemID%3D7342461256&affcode=a235412","image":"images/013fffedee.jpeg","price_jpy":2986,"model":null,"batch":null},{"seller":"kdi220","brand":"Lacoste","type":"TOPS","title":"€27.0 PH9633","yupoo":"https://kdi220.x.yupoo.com/albums/230340320?uid=1&isSubCate=true&referrercate=271667","kakobuy":"https://www.kakobuy.com/item/details?url=https%3A%2F%2Fwww.jadeship.com%2Fitem%2Fweidian%2F7718365103&affcode=a235412","image":"images/a835b3604c.png","price_jpy":4815,"model":null,"batch":null},{"seller":"kdi220","brand":"Lacoste","type":"TOPS","title":"€27.39 AH5339","yupoo":"https://kdi220.x.yupoo.com/albums/228879139?uid=1&isSubCate=true&referrercate=271667","kakobuy":"https://www.kakobuy.com/item/details?url=https%3A%2F%2Fwww.jadeship.com%2Fitem%2Fweidian%2F7705738751&affcode=a235412","image":"images/365b36e189.png","price_jpy":5070,"model":null,"batch":null},{"seller":"kdi220","brand":"Lacoste","type":"TOPS","title":"€26","yupoo":"https://kdi220.x.yupoo.com/albums/200300421?uid=1&isSubCate=true&referrercate=271667","kakobuy":"https://www.kakobuy.com/item/details?url=https%3A%2F%2Fwww.jadeship.com%2Fitem%2Fweidian%2F7262208936&affcode=a235412","image":"images/e261aeb269.png","price_jpy":3889,"model":null,"batch":null},{"seller":"kdi220","brand":"Lacoste","type":"TOPS","title":"€24.9 PH7561","yupoo":"https://kdi220.x.yupoo.com/albums/210982017?uid=1&isSubCate=true&referrercate=271667","kakobuy":"https://www.kakobuy.com/item/details?url=https%3A%2F%2Fwww.jadeship.com%2Fitem%2Fweidian%2F7556360240&affcode=a235412","image":"images/7c320611ad.jpg","price_jpy":4838,"model":null,"batch":null},{"seller":"kdi220","brand":"Lacoste","type":"TOPS","title":"€26 PH5305","yupoo":"https://kdi220.x.yupoo.com/albums/185606717?uid=1&isSubCate=true&referrercate=271667","kakobuy":"https://www.kakobuy.com/item/details?url=https%3A%2F%2Fwww.jadeship.com%2Fitem%2Fweidian%2F7380174983&affcode=a235412","image":"images/3bd9c01df7.jpg","price_jpy":3658,"model":null,"batch":null},{"seller":"kdi220","brand":"Lacoste","type":"TOPS","title":"€26 PH3760","yupoo":"https://kdi220.x.yupoo.com/albums/185606586?uid=1&isSubCate=true&referrercate=271667","kakobuy":"https://www.kakobuy.com/item/details?url=https%3A%2F%2Fshop1646496609.v.weidian.com%2Fitem.html%3FitemID%3D7382112292%26spider_token%3D1214&affcode=a235412","image":"images/7318f53a45.jpg","price_jpy":5070,"model":null,"batch":null},{"seller":"kdi220","brand":"Lacoste","type":"TOPS","title":"€26 PH7801","yupoo":"https://kdi220.x.yupoo.com/albums/185607152?uid=1&isSubCate=true&referrercate=271667","kakobuy":"https://www.kakobuy.com/item/details?url=https%3A%2F%2Fwww.jadeship.com%2Fitem%2Fweidian%2F7391669296&affcode=a235412","image":"images/53ddd4a619.jpg","price_jpy":5070,"model":null,"batch":null},{"seller":"kdi220","brand":"Lacoste","type":"TOPS","title":"€26 PH2723","yupoo":"https://kdi220.x.yupoo.com/albums/185607074?uid=1&isSubCate=true&referrercate=271667","kakobuy":"https://www.kakobuy.com/item/details?url=https%3A%2F%2Fwww.jadeship.com%2Fitem%2Fweidian%2F7391688934&affcode=a235412","image":"images/5855202026.jpg","price_jpy":5070,"model":null,"batch":null},{"seller":"kdi220","brand":"Lacoste","type":"TOPS","title":"€22.5 _slim fit 3 buttons.PH7937","yupoo":"https://kdi220.x.yupoo.com/albums/177118108?uid=1&isSubCate=true&referrercate=271667","kakobuy":"https://www.kakobuy.com/item/details?url=https%3A%2F%2Fwww.jadeship.com%2Fitem%2Fweidian%2F7265607544&affcode=a235412","image":"images/b53f11421d.jpg","price_jpy":4375,"model":null,"batch":null},{"seller":"kdi220","brand":"Lacoste","type":"TOPS","title":"€23.5 _PH5894","yupoo":"https://kdi220.x.yupoo.com/albums/177115603?uid=1&isSubCate=true&referrercate=271667","kakobuy":"https://www.kakobuy.com/item/details?url=https%3A%2F%2Fwww.jadeship.com%2Fitem%2Fweidian%2F7264627495&affcode=a235412","image":"images/33a9cbbfa7.jpg","price_jpy":4584,"model":null,"batch":null},{"seller":"kdi220","brand":"Lacoste","type":"TOPS","title":"€20 _PH038","yupoo":"https://kdi220.x.yupoo.com/albums/177115388?uid=1&isSubCate=true&referrercate=271667","kakobuy":"https://www.kakobuy.com/item/details?url=https%3A%2F%2Fshop1646496609.v.weidian.com%2Fitem.html%3FitemID%3D7265633420%26spider_token%3Deee8&affcode=a235412","image":"images/d0001d2751.jpg","price_jpy":3889,"model":null,"batch":null},{"seller":"kdi220","brand":"Lacoste","type":"TOPS","title":"€21_PH3839","yupoo":"https://kdi220.x.yupoo.com/albums/177037201?uid=1&isSubCate=true&referrercate=271667","kakobuy":"https://www.kakobuy.com/item/details?url=https%3A%2F%2Fwww.jadeship.com%2Fitem%2Fweidian%2F7252650534&affcode=a235412","image":"images/edcc748570.jpg","price_jpy":4121,"model":null,"batch":null},{"seller":"kdi220","brand":"Lacoste","type":"TOPS","title":"€23.6_regular fitPH8361","yupoo":"https://kdi220.x.yupoo.com/albums/177023766?uid=1&isSubCate=true&referrercate=271667","kakobuy":"https://www.kakobuy.com/item/details?url=https%3A%2F%2Fwww.jadeship.com%2Fitem%2Fweidian%2F7251705334&affcode=a235412","image":"images/682bf3453f.jpg","price_jpy":4607,"model":null,"batch":null},{"seller":"kdi220","brand":"Lacoste","type":"TOPS","title":"€23.6 regular fit_PH5522","yupoo":"https://kdi220.x.yupoo.com/albums/177023424?uid=1&isSubCate=true&referrercate=271667","kakobuy":"https://www.kakobuy.com/item/details?url=https%3A%2F%2Fwww.jadeship.com%2Fitem%2Fweidian%2F7251766696&affcode=a235412","image":"images/ceb0b20ec7.jpg","price_jpy":4607,"model":null,"batch":null},{"seller":"kdi220","brand":"Lacoste","type":"TOPS","title":"€20_PH7419","yupoo":"https://kdi220.x.yupoo.com/albums/177046477?uid=1&isSubCate=true&referrercate=271667","kakobuy":"https://www.kakobuy.com/item/details?url=https%3A%2F%2Fshop1646496609.v.weidian.com%2Fitem.html%3FitemID%3D7264661183%26spider_token%3Dd398&affcode=a235412","image":"images/9afce4fa13.jpg","price_jpy":5070,"model":null,"batch":null},{"seller":"kdi220","brand":"Lacoste","type":"TOPS","title":"€26_PH736","yupoo":"https://kdi220.x.yupoo.com/albums/177037978?uid=1&isSubCate=true&referrercate=271667","kakobuy":"https://www.kakobuy.com/item/details?url=https%3A%2F%2Fwww.jadeship.com%2Fitem%2Fweidian%2F7265682814&affcode=a235412","image":"images/77d2e5a245.jpg","price_jpy":5070,"model":null,"batch":null},{"seller":"kdi220","brand":"Lacoste","type":"TOPS","title":"€26_PH3839","yupoo":"https://kdi220.x.yupoo.com/albums/177037878?uid=1&isSubCate=true&referrercate=271667","kakobuy":"https://www.kakobuy.com/item/details?url=https%3A%2F%2Fshop1646496609.v.weidian.com%2Fitem.html%3FitemID%3D7265694384%26spider_token%3D67d1&affcode=a235412","image":"images/d853178908.jpg","price_jpy":5070,"model":null,"batch":null},{"seller":"kdi220","brand":"Lacoste","type":"TOPS","title":"€20","yupoo":"https://kdi220.x.yupoo.com/albums/177036953?uid=1&isSubCate=true&referrercate=271667","kakobuy":"https://www.kakobuy.com/item/details?url=https%3A%2F%2Fwww.jadeship.com%2Fitem%2Fweidian%2F7252654094&affcode=a235412","image":"images/c85f49ea26.jpg","price_jpy":3889,"model":null,"batch":null},{"seller":"kdi220","brand":"Lacoste","type":"TOPS","title":"€20_PH6238","yupoo":"https://kdi220.x.yupoo.com/albums/177036568?uid=1&isSubCate=true&referrercate=271667","kakobuy":"https://www.kakobuy.com/item/details?url=https%3A%2F%2Fwww.jadeship.com%2Fitem%2Fweidian%2F7251629253&affcode=a235412","image":"images/ef5fde6ec4.jpg","price_jpy":3889,"model":null,"batch":null},{"seller":"kdi220","brand":"Lacoste","type":"TOPS","title":"€20 _PH9116","yupoo":"https://kdi220.x.yupoo.com/albums/177031051?uid=1&isSubCate=true&referrercate=271667","kakobuy":"https://www.kakobuy.com/item/details?url=https%3A%2F%2Fwww.jadeship.com%2Fitem%2Fweidian%2F7251609427&affcode=a235412","image":"images/764e7b8124.jpg","price_jpy":3889,"model":null,"batch":null},{"seller":"kdi220","brand":"Lacoste","type":"TOPS","title":"€26_PH6351-98","yupoo":"https://kdi220.x.yupoo.com/albums/177030781?uid=1&isSubCate=true&referrercate=271667","kakobuy":"https://www.kakobuy.com/item/details?url=https%3A%2F%2Fshop1646496609.v.weidian.com%2Fitem.html%3FitemID%3D7251701767%26spider_token%3D14da&affcode=a235412","image":"images/774cb09fc8.jpg","price_jpy":5070,"model":null,"batch":null},{"seller":"kdi220","brand":"Lacoste","type":"TOPS","title":"€26_PH8017","yupoo":"https://kdi220.x.yupoo.com/albums/177024737?uid=1&isSubCate=true&referrercate=271667","kakobuy":"https://www.kakobuy.com/item/details?url=https%3A%2F%2Fshop1646496609.v.weidian.com%2Fitem.html%3FitemID%3D7250655157%26spider_token%3Dc99c&affcode=a235412","image":"images/4f2730bcfb.jpg","price_jpy":5070,"model":null,"batch":null},{"seller":"kdi220","brand":"Lacoste","type":"TOPS","title":"€23.5 _EF8470","yupoo":"https://kdi220.x.yupoo.com/albums/177029825?uid=1&isSubCate=true&referrercate=273392","kakobuy":"https://www.kakobuy.com/item/details?url=https%3A%2F%2Fshop1646496609.v.weidian.com%2Fitem.html%3FitemID%3D7252609336%26spider_token%3D0ef9&affcode=a235412","image":"images/192bb81536.jpg","price_jpy":4584,"model":null,"batch":null},{"seller":"kdi220","brand":"Lacoste","type":"TOPS","title":"€50 Waterproof Vest","yupoo":"https://kdi220.x.yupoo.com/albums/216337927?uid=1&isSubCate=true&referrercate=273135","kakobuy":"https://www.kakobuy.com/item/details?url=https%3A%2F%2Fwww.jadeship.com%2Fitem%2Fweidian%2F7288325027&affcode=a235412","image":"images/e46c13f7af.jpg","price_jpy":9677,"model":null,"batch":null},{"seller":"kdi220","brand":"Lacoste","type":"TOPS","title":"€52 DOWN VEST BH2886","yupoo":"https://kdi220.x.yupoo.com/albums/215612094?uid=1&isSubCate=true&referrercate=273135","kakobuy":"https://www.kakobuy.com/item/details?url=https%3A%2F%2Fwww.jadeship.com%2Fitem%2Fweidian%2F7591969191%3Fagent%3Dallchinabuy&affcode=a235412","image":"images/f9ed26f4e4.jpg","price_jpy":8982,"model":null,"batch":null},{"seller":"huskyreps","brand":"NIKE","type":"TOPS","title":"￥~399 N🔥C🔥A & N🔥K🔥COTTON VEST 44121220 (im 176CM 58KG iwear size M in the photo)","yupoo":"https://huskyreps.x.yupoo.com/albums/219773676?uid=1&isSubCate=false&referrercate=5003289","kakobuy":"https://www.kakobuy.com/item/details?url=https%3A%2F%2Fitem.taobao.com%2Fitem.htm%3Fft%3Dt%26id%3D1003375393774&affcode=a235412","image":"images/1e40bfbdd6.jpg","price_jpy":null,"model":"NOCTA","batch":null},{"seller":"noghost","brand":"SUPREME","type":"TOPS","title":"Supreme x True Religion Appliqué Polo（2colors","yupoo":"https://noghost.x.yupoo.com/albums/231545323?uid=1&isSubCate=false&referrercate=5058913","kakobuy":"https://www.kakobuy.com/item/details?url=https%3A%2F%2Fitem.taobao.com%2Fitem.htm%3Fft%3Dt%26id%3D1038739291601&affcode=a235412","image":"images/abadecedb0.jpg","price_jpy":null,"model":null,"batch":null},{"seller":"noghost","brand":"SUPREME","type":"TOPS","title":"Supreme 7 polo shirt","yupoo":"https://noghost.x.yupoo.com/albums/210520920?uid=1&isSubCate=false&referrercate=5058913","kakobuy":"https://www.kakobuy.com/item/details?url=https%3A%2F%2Fitem.taobao.com%2Fitem.htm%3Fft%3Dt%26id%3D1037484730534&affcode=a235412","image":"images/657c6bce77.jpeg","price_jpy":null,"model":null,"batch":null},{"seller":"noghost","brand":"SUPREME","type":"TOPS","title":"Supreme 7 polo shirt","yupoo":"https://noghost.x.yupoo.com/albums/202915322?uid=1&isSubCate=false&referrercate=5058913","kakobuy":"https://www.kakobuy.com/item/details?url=https%3A%2F%2Fitem.taobao.com%2Fitem.htm%3Fft%3Dt%26id%3D1037484730534&affcode=a235412","image":"images/be001ae137.jpeg","price_jpy":null,"model":null,"batch":null},{"seller":"noghost","brand":"SUPREME","type":"TOPS","title":"Supreme 7 polo shirt","yupoo":"https://noghost.x.yupoo.com/albums/208649509?uid=1&isSubCate=false&referrercate=5058913","kakobuy":"https://www.kakobuy.com/item/details?url=https%3A%2F%2Fitem.taobao.com%2Fitem.htm%3Fft%3Dt%26id%3D1037484730534&affcode=a235412","image":"images/0f8429d1e0.jpeg","price_jpy":null,"model":null,"batch":null},{"seller":"RepsKing","brand":"Moncler","type":"TOPS","title":"【125RMB】#PRO0ab Ciri Polo 希里POLO","yupoo":"https://repsking.x.yupoo.com/albums/224834950?uid=1&isSubCate=false&referrercate=4544589","kakobuy":"https://www.kakobuy.com/item/details?url=https%3A%2F%2Fweidian.com%2Fitem.html%3FitemID%3D7686129128&affcode=a235412","image":"https://photo.yupoo.com/repsking/a95c0c1c/medium.png","price_jpy":null},{"seller":"RepsKing","brand":"Moncler","type":"TOPS","title":"【120RMB】#PRO067 rubber badge POLO 橡皮标POLO","yupoo":"https://repsking.x.yupoo.com/albums/220643299?uid=1&isSubCate=false&referrercate=4544589","kakobuy":"https://www.kakobuy.com/item/details?url=https%3A%2F%2Fweidian.com%2Fitem.html%3FitemID%3D7639292754&affcode=a235412","image":"https://photo.yupoo.com/repsking/657aa8a1/medium.png","price_jpy":null},{"seller":"RepsKing","brand":"Moncler","type":"TOPS","title":"【120RMB】#PRO021 RCW POLO 后领织带POLO","yupoo":"https://repsking.x.yupoo.com/albums/161740911?uid=1&isSubCate=false&referrercate=4544589","kakobuy":"https://www.kakobuy.com/item/details?url=https%3A%2F%2Fweidian.com%2Fitem.html%3FitemID%3D7722261903&affcode=a235412","image":"https://photo.yupoo.com/repsking/56662e08/medium.jpg","price_jpy":null},{"seller":"YRX","brand":"Moncler","type":"TOPS","title":"Classic Short Polo","yupoo":"https://yrxvip.x.yupoo.com/albums/199429700?uid=1&isSubCate=false&referrercate=4626348","kakobuy":"https://www.kakobuy.com/item/details?url=https%3A%2F%2Fitem.taobao.com%2Fitem.htm%3Fid%3D941362400258&affcode=a235412","image":"https://photo.yupoo.com/yrxvip/326fcb99/medium.png","price_jpy":null},{"seller":"JIEYI168Y","brand":"Moncler","type":"TOPS","title":"Classice Freestyle Vest","yupoo":"https://jieyi168x.x.yupoo.com/albums/176425782?uid=1&isSubCate=false&referrercate=4690996","kakobuy":"https://www.kakobuy.com/item/details?url=https%3A%2F%2Fitem.taobao.com%2Fitem.htm%3Fspm%3Da2oq0.12575281.0.0.45e51debRbXfIn%26ft%3Dt%26id%3D657355832659&affcode=a235412","image":"https://photo.yupoo.com/jieyi168x/060f8f78/medium.jpg","price_jpy":null},{"seller":"CPReps","brand":"CP Company","type":"TOPS","title":"[120RMB]#ProID010 Piquet Striped Collar Polo 皮克POLO","yupoo":"https://cprepscn.x.yupoo.com/albums/167557844?uid=1&isSubCate=false&referrercate=4543871","kakobuy":"https://www.kakobuy.com/item/details?url=https%3A%2F%2Fitem.taobao.com%2Fitem.htm%3Fid%3D982421821266&affcode=a235412","image":"https://photo.yupoo.com/cprepscn/771e80a7/medium.jpeg","price_jpy":null},{"seller":"King-of-Goose","brand":"Canada Goose","type":"TOPS","title":"JUNCTION VEST 640","yupoo":"https://kog001.x.yupoo.com/albums/195349599?uid=1&isSubCate=false&referrercate=4890311","kakobuy":"https://www.kakobuy.com/item/details?url=https%3A%2F%2Fweidian.com%2Fitem.html%3FitemID%3D7464661624&affcode=a235412","image":"https://photo.yupoo.com/kog001/f92d57c3/medium.jpg","price_jpy":null},{"seller":"King-of-Goose","brand":"Canada Goose","type":"TOPS","title":"JUNCTION VEST BLACK BADGE 640","yupoo":"https://kog001.x.yupoo.com/albums/195349298?uid=1&isSubCate=false&referrercate=4890311","kakobuy":"https://www.kakobuy.com/item/details?url=https%3A%2F%2Fweidian.com%2Fitem.html%3FitemID%3D7464649664&affcode=a235412","image":"https://photo.yupoo.com/kog001/08508f9e/medium.jpg","price_jpy":null},{"seller":"King-of-Goose","brand":"Canada Goose","type":"TOPS","title":"CROFTON VEST - BLACK BADGE 640","yupoo":"https://kog001.x.yupoo.com/albums/145747288?uid=1&isSubCate=false&referrercate=3852409","kakobuy":"https://www.kakobuy.com/item/details?url=https%3A%2F%2Fweidian.com%2Fitem.html%3FitemID%3D7089804572&affcode=a235412","image":"https://photo.yupoo.com/kog001/ea3d1a57/medium.jpg","price_jpy":null},{"seller":"King-of-Goose","brand":"Canada Goose","type":"TOPS","title":"CROFTON VEST 640","yupoo":"https://kog001.x.yupoo.com/albums/145745501?uid=1&isSubCate=false&referrercate=3852409","kakobuy":"https://www.kakobuy.com/item/details?url=https%3A%2F%2Fweidian.com%2Fitem.html%3FitemID%3D7089064850&affcode=a235412","image":"https://photo.yupoo.com/kog001/b106d635/medium.jpg","price_jpy":null},{"seller":"Topami","brand":"Ami Paris","type":"TOPS","title":"2026小黑心POLO衫","yupoo":"https://amiparis.x.yupoo.com/albums/226124707?uid=1&isSubCate=false&referrercate=4994183","kakobuy":"https://www.kakobuy.com/item/details?url=https%3A%2F%2Fitem.taobao.com%2Fitem.htm%3Fid%3D1048644575190%26spm%3Da213gs.v2success.0.0.60aa4831Cfzdxv&affcode=a235412","image":"https://photo.yupoo.com/amiparis/63dd9659/medium.jpg","price_jpy":null},{"seller":"Topami","brand":"Ami Paris","type":"TOPS","title":"2025新款白色徽章POLO衫","yupoo":"https://amiparis.x.yupoo.com/albums/189651927?uid=1&isSubCate=false&referrercate=4672360","kakobuy":"https://www.kakobuy.com/item/details?url=https%3A%2F%2Fitem.taobao.com%2Fitem.htm%3Fid%3D907712907117%26spm%3Da213gs.v2success.0.0.23a24831yzueOJ&affcode=a235412","image":"https://photo.yupoo.com/amiparis/1a28c3c7/medium.jpg","price_jpy":null},{"seller":"Topami","brand":"Ami Paris","type":"TOPS","title":"经典小标志POLO衫","yupoo":"https://amiparis.x.yupoo.com/albums/172682903?uid=1&isSubCate=false&referrercate=4672360","kakobuy":"https://www.kakobuy.com/item/details?url=https%3A%2F%2Fitem.taobao.com%2Fitem.htm%3Fspm%3Da21dvs.23580594.0.0.52de2c1bqqSVk0%26ft%3Dt%26id%3D700520731295&affcode=a235412","image":"https://photo.yupoo.com/amiparis/51096012/medium.jpg","price_jpy":null},{"seller":"Qingyunzi","brand":"Luxury Bags","type":"TOPS","title":"CNFANS The solution to stop working","yupoo":"https://qingyunzi.x.yupoo.com/albums/224637240?uid=1&isSubCate=false&referrercate=4879640","kakobuy":"https://www.kakobuy.com/item/details?url=https%3A%2F%2Fwww.jadeship.com%2Fconverter&affcode=a235412","image":"https://photo.yupoo.com/qingyunzi/9277e2bb/medium.png","price_jpy":null},{"seller":"Newpd","brand":"Ralph Lauren","type":"TOPS","title":"LAC men Polo","yupoo":"https://newdp.x.yupoo.com/albums/236694120?uid=1","kakobuy":"https://www.kakobuy.com/item/details?url=https%3A%2F%2Fweidian.com%2Fitem.html%3FitemID%3D7755901151%26spider_token%3Db4f1&affcode=a235412","image":"https://photo.yupoo.com/newdp/c6860fc0b7/medium.jpeg","price_jpy":null},{"seller":"Newpd","brand":"Ralph Lauren","type":"TOPS","title":"LAC women Polo","yupoo":"https://newdp.x.yupoo.com/albums/236693388?uid=1","kakobuy":"https://www.kakobuy.com/item/details?url=https%3A%2F%2Fweidian.com%2Fitem.html%3FitemID%3D7755956813%26spider_token%3D7047&affcode=a235412","image":"https://photo.yupoo.com/newdp/43aaeea167/medium.jpeg","price_jpy":null},{"seller":"Newpd","brand":"Ralph Lauren","type":"TOPS","title":"new ami Polo","yupoo":"https://newdp.x.yupoo.com/albums/231513318?uid=1","kakobuy":"https://www.kakobuy.com/item/details?url=https%3A%2F%2Fshop1852083541.v.weidian.com%2Fitem.html%3FitemID%3D7726691929%26spider_token%3Dc41f&affcode=a235412","image":"https://photo.yupoo.com/newdp/c045ab45/medium.jpeg","price_jpy":null},{"seller":"Newpd","brand":"Ralph Lauren","type":"TOPS","title":"NEW RL POLO","yupoo":"https://newdp.x.yupoo.com/albums/193801502?uid=1","kakobuy":"https://www.kakobuy.com/item/details?url=https%3A%2F%2Fweidian.com%2Fitem.html%3FitemID%3D7466989521%26spider_token%3D841a&affcode=a235412","image":"https://photo.yupoo.com/newdp/2787485a/medium.jpg","price_jpy":null},{"seller":"Newpd","brand":"Ralph Lauren","type":"TOPS","title":"LACOS NEW POLO","yupoo":"https://newdp.x.yupoo.com/albums/193801940?uid=1","kakobuy":"https://www.kakobuy.com/item/details?url=https%3A%2F%2Fweidian.com%2Fitem.html%3FitemID%3D7468989648%26spider_token%3D85c4&affcode=a235412","image":"https://photo.yupoo.com/newdp/30c8a4a2/medium.jpg","price_jpy":null},{"seller":"Repkingdom","brand":"Ralph Lauren","type":"TOPS","title":"￥128##women Polo bear polo shirt 椰树小熊女款Polo Y","yupoo":"https://repkingdom.x.yupoo.com/albums/236948372?uid=1&isSubCate=false&referrercate=4373091","kakobuy":"https://www.kakobuy.com/item/details?url=https%3A%2F%2Fweidian.com%2Fitem.html%3FitemID%3D7761001432&affcode=a235412","image":"https://photo.yupoo.com/repkingdom/76a2c9fcac/medium.jpg","price_jpy":null},{"seller":"Repkingdom","brand":"Ralph Lauren","type":"TOPS","title":"￥155##Big Horse 20th Anniversary Polo大马20周年纪念版polo衫515274E","yupoo":"https://repkingdom.x.yupoo.com/albums/236385213?uid=1&isSubCate=false&referrercate=4373091","kakobuy":"https://www.kakobuy.com/item/details?url=https%3A%2F%2Fweidian.com%2Fitem.html%3FitemID%3D7758478334&affcode=a235412","image":"https://photo.yupoo.com/repkingdom/f3a56535eb/medium.jpg","price_jpy":null},{"seller":"Repkingdom","brand":"Ralph Lauren","type":"TOPS","title":"￥158##bear Polo shirt  插兜熊polo衫 Y","yupoo":"https://repkingdom.x.yupoo.com/albums/234612916?uid=1&isSubCate=false&referrercate=4373091","kakobuy":"https://www.kakobuy.com/item/details?url=https%3A%2F%2Fweidian.com%2Fitem.html%3FitemID%3D7746516914&affcode=a235412","image":"https://photo.yupoo.com/repkingdom/ce9b3d5273/medium.jpg","price_jpy":null},{"seller":"Repkingdom","brand":"Ralph Lauren","type":"TOPS","title":"￥168##long sleeve Polo shirt  双扣长袖polo衫 Z","yupoo":"https://repkingdom.x.yupoo.com/albums/232951345?uid=1&isSubCate=false&referrercate=4373091","kakobuy":"https://www.kakobuy.com/item/details?url=https%3A%2F%2Fweidian.com%2Fitem.html%3FitemID%3D7738015062&affcode=a235412","image":"https://photo.yupoo.com/repkingdom/2911bc2d1a/medium.jpg","price_jpy":null},{"seller":"Repkingdom","brand":"Ralph Lauren","type":"TOPS","title":"￥158##Golf Po Bear Polo Shirt   小熊三色polo Y","yupoo":"https://repkingdom.x.yupoo.com/albums/231941715?uid=1&isSubCate=false&referrercate=4373091","kakobuy":"https://www.kakobuy.com/item/details?url=https%3A%2F%2Fweidian.com%2Fitem.html%3FitemID%3D7731939632&affcode=a235412","image":"https://photo.yupoo.com/repkingdom/2e923c51/medium.jpg","price_jpy":null}]}